Andreani_QA_Selenium/Selenium.py
Andreani_QA_Selenium/__init__.py
Andreani_QA_Selenium-0.0.59.dist-info/METADATA
Andreani_QA_Selenium-0.0.59.dist-info/WHEEL
Andreani_QA_Selenium-0.0.59.dist-info/top_level.txt
Andreani_QA_Selenium-0.0.59.dist-info/RECORD
